MANIFEST.in
README.md
setup.py
candumpgen/__init__.py
candumpgen/__main__.py
candumpgen/candumpgen.py
candumpgen/maybe_open.py
candumpgen/project.py
candumpgen/py.typed
candumpgen/version.py
candumpgen.egg-info/PKG-INFO
candumpgen.egg-info/SOURCES.txt
candumpgen.egg-info/dependency_links.txt
candumpgen.egg-info/entry_points.txt
candumpgen.egg-info/not-zip-safe
candumpgen.egg-info/requires.txt
candumpgen.egg-info/top_level.txt